octopwnremote/__init__.py
octopwnremote/_version.py
octopwnremote/base.py
octopwnremote/client.py
octopwnremote/proxy.py
octopwnremote/proxybase.py
octopwnremote/server.py
octopwnremote/examples/__init__.py
octopwnremote/examples/basic_example.py
octopwnremote/examples/hashcat.py
octopwnremote/examples/mcptest.py
octopwnremote/utils/__init__.py
octopwnremote/utils/processmanager.py
octopwnremote-0.0.3.dist-info/LICENSE
octopwnremote-0.0.3.dist-info/METADATA
octopwnremote-0.0.3.dist-info/WHEEL
octopwnremote-0.0.3.dist-info/entry_points.txt
octopwnremote-0.0.3.dist-info/top_level.txt
octopwnremote-0.0.3.dist-info/RECORD
