Metadata-Version: 2.1
Name: octopwnremote
Version: 0.0.3
Summary: API for OctoPwn's REMOTECONTROLJS and REMOTECONTROL module
Home-page: https://github.com/octopwn/octopwnremote
Author: Tamas Jos
Author-email: tamas.jos@octopwn.com
Classifier: Programming Language :: Python :: 3.7
Classifier: Programming Language :: Python :: 3.8
Classifier: License :: OSI Approved :: MIT License
Classifier: Operating System :: OS Independent
Requires-Python: >=3.7
License-File: LICENSE
Requires-Dist: websockets
